noohayo/__init__.py
noohayo/noohayo.py
noohayo/scripts/Colorer.py
noohayo/scripts/Config.py
noohayo/scripts/Fetch.py
noohayo/scripts/General.py
noohayo/scripts/Help.py
noohayo/scripts/Select.py
noohayo/scripts/__init__.py
noohayo-1.0.4.dist-info/METADATA
noohayo-1.0.4.dist-info/WHEEL
noohayo-1.0.4.dist-info/entry_points.txt
noohayo-1.0.4.dist-info/top_level.txt
noohayo-1.0.4.dist-info/RECORD
