Metadata-Version: 2.1
Name: noohayo
Version: 1.0.4
Summary: command line interface tool that displays a banner when ever you open a new ternimal tab.
Requires-Dist: argparse
Requires-Dist: appdirs
Requires-Dist: psutil
